lilium/__init__.py
lilium/manganelo/__init__.py
lilium/manganelo/manganelo.py
lilium/manganelo/manganeloChapter.py
lilium/manganelo/manganeloManga.py
lilium-2.0.1.dist-info/METADATA
lilium-2.0.1.dist-info/WHEEL
lilium-2.0.1.dist-info/licenses/LICENSE
lilium-2.0.1.dist-info/RECORD
